seolpyo_mplchart/__init__.py
seolpyo_mplchart/_base.py
seolpyo_mplchart/_cursor.py
seolpyo_mplchart/_draw.py
seolpyo_mplchart/_slider.py
seolpyo_mplchart/base.py
seolpyo_mplchart/cursor.py
seolpyo_mplchart/draw.py
seolpyo_mplchart/slider.py
seolpyo_mplchart/test.py
seolpyo_mplchart/utils.py
seolpyo_mplchart/xl_to_dict.py
seolpyo_mplchart/_chart/__init__.py
seolpyo_mplchart/_chart/_base.py
seolpyo_mplchart/_chart/test.py
seolpyo_mplchart/_chart/_cursor/__init__.py
seolpyo_mplchart/_chart/_cursor/_artist.py
seolpyo_mplchart/_chart/_cursor/_cursor.py
seolpyo_mplchart/_chart/_cursor/_info.py
seolpyo_mplchart/_chart/_draw/__init__.py
seolpyo_mplchart/_chart/_draw/_artist.py
seolpyo_mplchart/_chart/_draw/_data.py
seolpyo_mplchart/_chart/_draw/_draw.py
seolpyo_mplchart/_chart/_draw/_lim.py
seolpyo_mplchart/_chart/_slider/__init__.py
seolpyo_mplchart/_chart/_slider/_base.py
seolpyo_mplchart/_chart/_slider/_data.py
seolpyo_mplchart/_chart/_slider/_mouse.py
seolpyo_mplchart/_chart/_slider/_nav.py
seolpyo_mplchart/_chart/base/__init__.py
seolpyo_mplchart/_chart/base/a_canvas.py
seolpyo_mplchart/_chart/base/b_artist.py
seolpyo_mplchart/_chart/base/c_draw.py
seolpyo_mplchart/_chart/base/d_segment.py
seolpyo_mplchart/_chart/base/e_axis.py
seolpyo_mplchart/_chart/base/f_background.py
seolpyo_mplchart/_chart/base/g_event.py
seolpyo_mplchart/_chart/base/h_data.py
seolpyo_mplchart/_chart/base/test.py
seolpyo_mplchart/_chart/cursor/__init__.py
seolpyo_mplchart/_chart/cursor/b_artist.py
seolpyo_mplchart/_chart/cursor/c_draw.py
seolpyo_mplchart/_chart/cursor/d_segment.py
seolpyo_mplchart/_chart/cursor/e_axis.py
seolpyo_mplchart/_chart/cursor/g_event.py
seolpyo_mplchart/_chart/cursor/h_data.py
seolpyo_mplchart/_chart/cursor/test.py
seolpyo_mplchart/_chart/slider/__init__.py
seolpyo_mplchart/_chart/slider/a_canvas.py
seolpyo_mplchart/_chart/slider/b_artist.py
seolpyo_mplchart/_chart/slider/c_draw.py
seolpyo_mplchart/_chart/slider/d_segment.py
seolpyo_mplchart/_chart/slider/e_axis.py
seolpyo_mplchart-2.1.1.3.dist-info/METADATA
seolpyo_mplchart-2.1.1.3.dist-info/WHEEL
seolpyo_mplchart-2.1.1.3.dist-info/top_level.txt
seolpyo_mplchart-2.1.1.3.dist-info/RECORD
